hartufo/__init__.py
hartufo/checksums.py
hartufo/datareader.py
hartufo/display.py
hartufo/full.py
hartufo/planar.py
hartufo/query.py
hartufo/specifications.py
hartufo/util.py
hartufo/sklearn/__init__.py
hartufo/torch/__init__.py
hartufo/transforms/__init__.py
hartufo/transforms/hrir.py
hartufo/transforms/image.py
hartufo-0.6.6.dist-info/LICENSE
hartufo-0.6.6.dist-info/WHEEL
hartufo-0.6.6.dist-info/METADATA
hartufo-0.6.6.dist-info/RECORD
