Metadata-Version: 2.1
Name: hartufo
Version: 0.6.6
Summary: A Python toolkit for data-driven HRTF research
Author-email: Johan Pauwels <johan.pauwels@gmail.com>
Requires-Python: >=3.8
Classifier: License :: OSI Approved :: Apache Software License
Requires-Dist: matplotlib >=3.5
Requires-Dist: netCDF4 >=1.5
Requires-Dist: numpy >=1.22
Requires-Dist: openpyxl >=3.1
Requires-Dist: Pillow >=9
Requires-Dist: pymatreader >=0.0.32
Requires-Dist: samplerate >=0.1.0
Requires-Dist: scipy >=1.7
Requires-Dist: torchvision >=0.11
Requires-Dist: tqdm
Project-URL: Changelog, https://github.com/jpauwels/hartufo/releases
Project-URL: Home, https://github.com/jpauwels/hartufo
Project-URL: Issues, https://github.com/jpauwels/hartufo/issues
